{"audioUrl":"https://pub-ec086546d4bd484d9518e7dad253ff6e.r2.dev/05-alafasy-murattal-ar/015.mp3","totalDurationMs":954723,"timings":[{"verseNumber":1,"timestampFromMs":6580,"timestampToMs":18220},{"verseNumber":2,"timestampFromMs":18220,"timestampToMs":25020},{"verseNumber":3,"timestampFromMs":25020,"timestampToMs":33720},{"verseNumber":4,"timestampFromMs":33720,"timestampToMs":44220},{"verseNumber":5,"timestampFromMs":44220,"timestampToMs":52160},{"verseNumber":6,"timestampFromMs":52160,"timestampToMs":62980},{"verseNumber":7,"timestampFromMs":62980,"timestampToMs":73080},{"verseNumber":8,"timestampFromMs":73080,"timestampToMs":86180},{"verseNumber":9,"timestampFromMs":86180,"timestampToMs":95160},{"verseNumber":10,"timestampFromMs":95160,"timestampToMs":102400},{"verseNumber":11,"timestampFromMs":102400,"timestampToMs":111300},{"verseNumber":12,"timestampFromMs":111300,"timestampToMs":117320},{"verseNumber":13,"timestampFromMs":117320,"timestampToMs":125140},{"verseNumber":14,"timestampFromMs":125140,"timestampToMs":136860},{"verseNumber":15,"timestampFromMs":136860,"timestampToMs":148660},{"verseNumber":16,"timestampFromMs":148660,"timestampToMs":160340},{"verseNumber":17,"timestampFromMs":160340,"timestampToMs":166920},{"verseNumber":18,"timestampFromMs":166920,"timestampToMs":175220},{"verseNumber":19,"timestampFromMs":175220,"timestampToMs":192000},{"verseNumber":20,"timestampFromMs":192000,"timestampToMs":201140},{"verseNumber":21,"timestampFromMs":201140,"timestampToMs":216780},{"verseNumber":22,"timestampFromMs":216780,"timestampToMs":240720},{"verseNumber":23,"timestampFromMs":240720,"timestampToMs":248720},{"verseNumber":24,"timestampFromMs":248720,"timestampToMs":258220},{"verseNumber":25,"timestampFromMs":258220,"timestampToMs":267540},{"verseNumber":26,"timestampFromMs":267540,"timestampToMs":279320},{"verseNumber":27,"timestampFromMs":279320,"timestampToMs":292240},{"verseNumber":28,"timestampFromMs":292240,"timestampToMs":308280},{"verseNumber":29,"timestampFromMs":308280,"timestampToMs":317840},{"verseNumber":30,"timestampFromMs":317840,"timestampToMs":325260},{"verseNumber":31,"timestampFromMs":325260,"timestampToMs":335020},{"verseNumber":32,"timestampFromMs":335020,"timestampToMs":343680},{"verseNumber":33,"timestampFromMs":343680,"timestampToMs":356620},{"verseNumber":34,"timestampFromMs":356620,"timestampToMs":363240},{"verseNumber":35,"timestampFromMs":363240,"timestampToMs":370100},{"verseNumber":36,"timestampFromMs":370100,"timestampToMs":380060},{"verseNumber":37,"timestampFromMs":380060,"timestampToMs":386500},{"verseNumber":38,"timestampFromMs":386500,"timestampToMs":391420},{"verseNumber":39,"timestampFromMs":391420,"timestampToMs":405400},{"verseNumber":40,"timestampFromMs":405400,"timestampToMs":411080},{"verseNumber":41,"timestampFromMs":411080,"timestampToMs":417380},{"verseNumber":42,"timestampFromMs":417380,"timestampToMs":428780},{"verseNumber":43,"timestampFromMs":428780,"timestampToMs":435920},{"verseNumber":44,"timestampFromMs":435920,"timestampToMs":448060},{"verseNumber":45,"timestampFromMs":448060,"timestampToMs":457000},{"verseNumber":46,"timestampFromMs":457000,"timestampToMs":463080},{"verseNumber":47,"timestampFromMs":463080,"timestampToMs":474020},{"verseNumber":48,"timestampFromMs":474020,"timestampToMs":484560},{"verseNumber":49,"timestampFromMs":484560,"timestampToMs":496060},{"verseNumber":50,"timestampFromMs":496060,"timestampToMs":503620},{"verseNumber":51,"timestampFromMs":503620,"timestampToMs":510380},{"verseNumber":52,"timestampFromMs":510380,"timestampToMs":521740},{"verseNumber":53,"timestampFromMs":521740,"timestampToMs":530440},{"verseNumber":54,"timestampFromMs":530440,"timestampToMs":541440},{"verseNumber":55,"timestampFromMs":541440,"timestampToMs":550260},{"verseNumber":56,"timestampFromMs":550260,"timestampToMs":563580},{"verseNumber":57,"timestampFromMs":563580,"timestampToMs":569900},{"verseNumber":58,"timestampFromMs":569900,"timestampToMs":581540},{"verseNumber":59,"timestampFromMs":581540,"timestampToMs":590860},{"verseNumber":60,"timestampFromMs":590860,"timestampToMs":600520},{"verseNumber":61,"timestampFromMs":600520,"timestampToMs":608660},{"verseNumber":62,"timestampFromMs":608660,"timestampToMs":615820},{"verseNumber":63,"timestampFromMs":615820,"timestampToMs":623700},{"verseNumber":64,"timestampFromMs":623700,"timestampToMs":631020},{"verseNumber":65,"timestampFromMs":631020,"timestampToMs":647020},{"verseNumber":66,"timestampFromMs":647020,"timestampToMs":663620},{"verseNumber":67,"timestampFromMs":663620,"timestampToMs":671040},{"verseNumber":68,"timestampFromMs":671040,"timestampToMs":681160},{"verseNumber":69,"timestampFromMs":681160,"timestampToMs":686220},{"verseNumber":70,"timestampFromMs":686220,"timestampToMs":693540},{"verseNumber":71,"timestampFromMs":693540,"timestampToMs":705580},{"verseNumber":72,"timestampFromMs":705580,"timestampToMs":712940},{"verseNumber":73,"timestampFromMs":712940,"timestampToMs":718380},{"verseNumber":74,"timestampFromMs":718380,"timestampToMs":734880},{"verseNumber":75,"timestampFromMs":734880,"timestampToMs":742500},{"verseNumber":76,"timestampFromMs":742500,"timestampToMs":749060},{"verseNumber":77,"timestampFromMs":749060,"timestampToMs":756680},{"verseNumber":78,"timestampFromMs":756680,"timestampToMs":764240},{"verseNumber":79,"timestampFromMs":764240,"timestampToMs":774500},{"verseNumber":80,"timestampFromMs":774500,"timestampToMs":781600},{"verseNumber":81,"timestampFromMs":781600,"timestampToMs":789880},{"verseNumber":82,"timestampFromMs":789880,"timestampToMs":797740},{"verseNumber":83,"timestampFromMs":797740,"timestampToMs":803000},{"verseNumber":84,"timestampFromMs":803000,"timestampToMs":812040},{"verseNumber":85,"timestampFromMs":812040,"timestampToMs":831400},{"verseNumber":86,"timestampFromMs":831400,"timestampToMs":837940},{"verseNumber":87,"timestampFromMs":837940,"timestampToMs":848380},{"verseNumber":88,"timestampFromMs":848380,"timestampToMs":870080},{"verseNumber":89,"timestampFromMs":870080,"timestampToMs":878120},{"verseNumber":90,"timestampFromMs":878120,"timestampToMs":887680},{"verseNumber":91,"timestampFromMs":887680,"timestampToMs":894000},{"verseNumber":92,"timestampFromMs":894000,"timestampToMs":900540},{"verseNumber":93,"timestampFromMs":900540,"timestampToMs":905980},{"verseNumber":94,"timestampFromMs":905980,"timestampToMs":913140},{"verseNumber":95,"timestampFromMs":913140,"timestampToMs":919560},{"verseNumber":96,"timestampFromMs":919560,"timestampToMs":930460},{"verseNumber":97,"timestampFromMs":930460,"timestampToMs":938580},{"verseNumber":98,"timestampFromMs":938580,"timestampToMs":946640},{"verseNumber":99,"timestampFromMs":946640,"timestampToMs":951960}],"alignment":{"source":"ctc-forced-aligner:jonatasgrosman/wav2vec2-large-xlsr-53-arabic","wordMatchRatio":1.0,"alignedAt":"2026-04-20T19:40:18+00:00"}}