{"audioUrl":"https://pub-ec086546d4bd484d9518e7dad253ff6e.r2.dev/05-alafasy-murattal-ar/068.mp3","totalDurationMs":456072,"timings":[{"verseNumber":1,"timestampFromMs":32700,"timestampToMs":33480},{"verseNumber":2,"timestampFromMs":33500,"timestampToMs":34240},{"verseNumber":3,"timestampFromMs":34260,"timestampToMs":35120},{"verseNumber":4,"timestampFromMs":35140,"timestampToMs":37520},{"verseNumber":5,"timestampFromMs":37520,"timestampToMs":41520},{"verseNumber":6,"timestampFromMs":41520,"timestampToMs":45620},{"verseNumber":7,"timestampFromMs":45620,"timestampToMs":57880},{"verseNumber":8,"timestampFromMs":57880,"timestampToMs":62500},{"verseNumber":9,"timestampFromMs":62500,"timestampToMs":68600},{"verseNumber":10,"timestampFromMs":68600,"timestampToMs":75220},{"verseNumber":11,"timestampFromMs":75220,"timestampToMs":84120},{"verseNumber":12,"timestampFromMs":84120,"timestampToMs":91120},{"verseNumber":13,"timestampFromMs":91120,"timestampToMs":97980},{"verseNumber":14,"timestampFromMs":97980,"timestampToMs":105520},{"verseNumber":15,"timestampFromMs":105520,"timestampToMs":114060},{"verseNumber":16,"timestampFromMs":114060,"timestampToMs":120120},{"verseNumber":17,"timestampFromMs":120120,"timestampToMs":135660},{"verseNumber":18,"timestampFromMs":135660,"timestampToMs":140220},{"verseNumber":19,"timestampFromMs":140220,"timestampToMs":151560},{"verseNumber":20,"timestampFromMs":151560,"timestampToMs":154960},{"verseNumber":21,"timestampFromMs":154960,"timestampToMs":160020},{"verseNumber":22,"timestampFromMs":160020,"timestampToMs":168220},{"verseNumber":23,"timestampFromMs":168220,"timestampToMs":174700},{"verseNumber":24,"timestampFromMs":174700,"timestampToMs":183020},{"verseNumber":25,"timestampFromMs":183020,"timestampToMs":189760},{"verseNumber":26,"timestampFromMs":189760,"timestampToMs":202000},{"verseNumber":27,"timestampFromMs":202000,"timestampToMs":206640},{"verseNumber":28,"timestampFromMs":206640,"timestampToMs":214540},{"verseNumber":29,"timestampFromMs":214540,"timestampToMs":225140},{"verseNumber":30,"timestampFromMs":225140,"timestampToMs":232860},{"verseNumber":31,"timestampFromMs":232860,"timestampToMs":242680},{"verseNumber":32,"timestampFromMs":242680,"timestampToMs":258440},{"verseNumber":33,"timestampFromMs":258440,"timestampToMs":273160},{"verseNumber":34,"timestampFromMs":273160,"timestampToMs":282500},{"verseNumber":35,"timestampFromMs":282500,"timestampToMs":289680},{"verseNumber":36,"timestampFromMs":289680,"timestampToMs":294620},{"verseNumber":37,"timestampFromMs":294620,"timestampToMs":300700},{"verseNumber":38,"timestampFromMs":300700,"timestampToMs":306820},{"verseNumber":39,"timestampFromMs":306820,"timestampToMs":318680},{"verseNumber":40,"timestampFromMs":318680,"timestampToMs":324980},{"verseNumber":41,"timestampFromMs":324980,"timestampToMs":337800},{"verseNumber":42,"timestampFromMs":337800,"timestampToMs":347300},{"verseNumber":43,"timestampFromMs":347300,"timestampToMs":361060},{"verseNumber":44,"timestampFromMs":361060,"timestampToMs":375000},{"verseNumber":45,"timestampFromMs":375000,"timestampToMs":381640},{"verseNumber":46,"timestampFromMs":381640,"timestampToMs":391720},{"verseNumber":47,"timestampFromMs":391720,"timestampToMs":398400},{"verseNumber":48,"timestampFromMs":398400,"timestampToMs":409440},{"verseNumber":49,"timestampFromMs":409440,"timestampToMs":423980},{"verseNumber":50,"timestampFromMs":423980,"timestampToMs":431300},{"verseNumber":51,"timestampFromMs":431300,"timestampToMs":447320},{"verseNumber":52,"timestampFromMs":447320,"timestampToMs":456040}],"alignment":{"source":"ctc-forced-aligner:jonatasgrosman/wav2vec2-large-xlsr-53-arabic","wordMatchRatio":1.0,"alignedAt":"2026-04-20T20:37:29+00:00"}}