{"audioUrl":"https://pub-ec086546d4bd484d9518e7dad253ff6e.r2.dev/07-sudais-murattal-ar/057.mp3","totalDurationMs":527438,"timings":[{"verseNumber":1,"timestampFromMs":3600,"timestampToMs":9960},{"verseNumber":2,"timestampFromMs":9960,"timestampToMs":17480},{"verseNumber":3,"timestampFromMs":17480,"timestampToMs":24380},{"verseNumber":4,"timestampFromMs":24380,"timestampToMs":47180},{"verseNumber":5,"timestampFromMs":47180,"timestampToMs":52860},{"verseNumber":6,"timestampFromMs":52860,"timestampToMs":61380},{"verseNumber":7,"timestampFromMs":61380,"timestampToMs":76220},{"verseNumber":8,"timestampFromMs":76220,"timestampToMs":88400},{"verseNumber":9,"timestampFromMs":88400,"timestampToMs":101520},{"verseNumber":10,"timestampFromMs":101520,"timestampToMs":131700},{"verseNumber":11,"timestampFromMs":131700,"timestampToMs":141300},{"verseNumber":12,"timestampFromMs":141300,"timestampToMs":162440},{"verseNumber":13,"timestampFromMs":162440,"timestampToMs":187580},{"verseNumber":14,"timestampFromMs":187580,"timestampToMs":210420},{"verseNumber":15,"timestampFromMs":210420,"timestampToMs":222680},{"verseNumber":16,"timestampFromMs":222680,"timestampToMs":251940},{"verseNumber":17,"timestampFromMs":251940,"timestampToMs":262040},{"verseNumber":18,"timestampFromMs":262040,"timestampToMs":272660},{"verseNumber":19,"timestampFromMs":272660,"timestampToMs":296340},{"verseNumber":20,"timestampFromMs":296340,"timestampToMs":332080},{"verseNumber":21,"timestampFromMs":332080,"timestampToMs":364680},{"verseNumber":22,"timestampFromMs":364680,"timestampToMs":377460},{"verseNumber":23,"timestampFromMs":377460,"timestampToMs":392340},{"verseNumber":24,"timestampFromMs":392340,"timestampToMs":404880},{"verseNumber":25,"timestampFromMs":404880,"timestampToMs":432420},{"verseNumber":26,"timestampFromMs":432420,"timestampToMs":447120},{"verseNumber":27,"timestampFromMs":447120,"timestampToMs":485980},{"verseNumber":28,"timestampFromMs":485980,"timestampToMs":504040},{"verseNumber":29,"timestampFromMs":504040,"timestampToMs":516340}],"alignment":{"source":"ctc-forced-aligner:jonatasgrosman/wav2vec2-large-xlsr-53-arabic","wordMatchRatio":1.0,"alignedAt":"2026-04-21T09:40:38+00:00"}}