{"audioUrl":"https://pub-ec086546d4bd484d9518e7dad253ff6e.r2.dev/37-abdulbaset-murattal-ar/040.mp3","totalDurationMs":1698377,"timings":[{"verseNumber":1,"timestampFromMs":4900,"timestampToMs":7780},{"verseNumber":2,"timestampFromMs":7780,"timestampToMs":17700},{"verseNumber":3,"timestampFromMs":17700,"timestampToMs":36280},{"verseNumber":4,"timestampFromMs":36280,"timestampToMs":52300},{"verseNumber":5,"timestampFromMs":52300,"timestampToMs":85160},{"verseNumber":6,"timestampFromMs":85160,"timestampToMs":100180},{"verseNumber":7,"timestampFromMs":100200,"timestampToMs":139740},{"verseNumber":8,"timestampFromMs":139740,"timestampToMs":166360},{"verseNumber":9,"timestampFromMs":166360,"timestampToMs":184340},{"verseNumber":10,"timestampFromMs":184340,"timestampToMs":204440},{"verseNumber":11,"timestampFromMs":204440,"timestampToMs":224600},{"verseNumber":12,"timestampFromMs":224600,"timestampToMs":247260},{"verseNumber":13,"timestampFromMs":247260,"timestampToMs":266240},{"verseNumber":14,"timestampFromMs":266240,"timestampToMs":275620},{"verseNumber":15,"timestampFromMs":275620,"timestampToMs":294880},{"verseNumber":16,"timestampFromMs":294880,"timestampToMs":314300},{"verseNumber":17,"timestampFromMs":314300,"timestampToMs":331820},{"verseNumber":18,"timestampFromMs":331820,"timestampToMs":353960},{"verseNumber":19,"timestampFromMs":353960,"timestampToMs":362780},{"verseNumber":20,"timestampFromMs":362780,"timestampToMs":383360},{"verseNumber":21,"timestampFromMs":383360,"timestampToMs":422440},{"verseNumber":22,"timestampFromMs":422440,"timestampToMs":443180},{"verseNumber":23,"timestampFromMs":443180,"timestampToMs":452960},{"verseNumber":24,"timestampFromMs":452960,"timestampToMs":462820},{"verseNumber":25,"timestampFromMs":462820,"timestampToMs":492580},{"verseNumber":26,"timestampFromMs":492580,"timestampToMs":513940},{"verseNumber":27,"timestampFromMs":513940,"timestampToMs":530020},{"verseNumber":28,"timestampFromMs":530020,"timestampToMs":581080},{"verseNumber":29,"timestampFromMs":581080,"timestampToMs":612660},{"verseNumber":30,"timestampFromMs":612660,"timestampToMs":626360},{"verseNumber":31,"timestampFromMs":626360,"timestampToMs":643460},{"verseNumber":32,"timestampFromMs":643460,"timestampToMs":652100},{"verseNumber":33,"timestampFromMs":652100,"timestampToMs":667880},{"verseNumber":34,"timestampFromMs":667880,"timestampToMs":704220},{"verseNumber":35,"timestampFromMs":704220,"timestampToMs":733260},{"verseNumber":36,"timestampFromMs":733260,"timestampToMs":744520},{"verseNumber":37,"timestampFromMs":744520,"timestampToMs":775320},{"verseNumber":38,"timestampFromMs":775320,"timestampToMs":786120},{"verseNumber":39,"timestampFromMs":786120,"timestampToMs":800660},{"verseNumber":40,"timestampFromMs":800660,"timestampToMs":838040},{"verseNumber":41,"timestampFromMs":838040,"timestampToMs":851560},{"verseNumber":42,"timestampFromMs":851560,"timestampToMs":867280},{"verseNumber":43,"timestampFromMs":867280,"timestampToMs":903100},{"verseNumber":44,"timestampFromMs":903100,"timestampToMs":922100},{"verseNumber":45,"timestampFromMs":922100,"timestampToMs":935280},{"verseNumber":46,"timestampFromMs":935280,"timestampToMs":956240},{"verseNumber":47,"timestampFromMs":956240,"timestampToMs":1001620},{"verseNumber":48,"timestampFromMs":1001620,"timestampToMs":1018120},{"verseNumber":49,"timestampFromMs":1018120,"timestampToMs":1033940},{"verseNumber":50,"timestampFromMs":1033940,"timestampToMs":1057840},{"verseNumber":51,"timestampFromMs":1057840,"timestampToMs":1072020},{"verseNumber":52,"timestampFromMs":1072020,"timestampToMs":1085480},{"verseNumber":53,"timestampFromMs":1085480,"timestampToMs":1097920},{"verseNumber":54,"timestampFromMs":1097920,"timestampToMs":1103820},{"verseNumber":55,"timestampFromMs":1103820,"timestampToMs":1120560},{"verseNumber":56,"timestampFromMs":1120560,"timestampToMs":1151920},{"verseNumber":57,"timestampFromMs":1151920,"timestampToMs":1167460},{"verseNumber":58,"timestampFromMs":1167460,"timestampToMs":1186680},{"verseNumber":59,"timestampFromMs":1186680,"timestampToMs":1200900},{"verseNumber":60,"timestampFromMs":1200900,"timestampToMs":1220700},{"verseNumber":61,"timestampFromMs":1220700,"timestampToMs":1247020},{"verseNumber":62,"timestampFromMs":1247020,"timestampToMs":1261740},{"verseNumber":63,"timestampFromMs":1261740,"timestampToMs":1270960},{"verseNumber":64,"timestampFromMs":1270960,"timestampToMs":1302120},{"verseNumber":65,"timestampFromMs":1302120,"timestampToMs":1318680},{"verseNumber":66,"timestampFromMs":1318680,"timestampToMs":1342400},{"verseNumber":67,"timestampFromMs":1342400,"timestampToMs":1395720},{"verseNumber":68,"timestampFromMs":1395720,"timestampToMs":1411520},{"verseNumber":69,"timestampFromMs":1411520,"timestampToMs":1423940},{"verseNumber":70,"timestampFromMs":1423940,"timestampToMs":1436740},{"verseNumber":71,"timestampFromMs":1436740,"timestampToMs":1445880},{"verseNumber":72,"timestampFromMs":1445880,"timestampToMs":1452500},{"verseNumber":73,"timestampFromMs":1452500,"timestampToMs":1461080},{"verseNumber":74,"timestampFromMs":1461080,"timestampToMs":1479660},{"verseNumber":75,"timestampFromMs":1479660,"timestampToMs":1494120},{"verseNumber":76,"timestampFromMs":1494120,"timestampToMs":1507920},{"verseNumber":77,"timestampFromMs":1507920,"timestampToMs":1527700},{"verseNumber":78,"timestampFromMs":1527700,"timestampToMs":1566520},{"verseNumber":79,"timestampFromMs":1566520,"timestampToMs":1578240},{"verseNumber":80,"timestampFromMs":1578240,"timestampToMs":1594360},{"verseNumber":81,"timestampFromMs":1594360,"timestampToMs":1604320},{"verseNumber":82,"timestampFromMs":1604320,"timestampToMs":1636800},{"verseNumber":83,"timestampFromMs":1636800,"timestampToMs":1658280},{"verseNumber":84,"timestampFromMs":1658280,"timestampToMs":1675860},{"verseNumber":85,"timestampFromMs":1675860,"timestampToMs":1698020}],"alignment":{"source":"ctc-forced-aligner:jonatasgrosman/wav2vec2-large-xlsr-53-arabic","wordMatchRatio":1.0,"alignedAt":"2026-04-21T17:28:30+00:00"}}