{"audioUrl":"https://pub-ec086546d4bd484d9518e7dad253ff6e.r2.dev/37-abdulbaset-murattal-ar/009.mp3","totalDurationMs":3276957,"timings":[{"verseNumber":1,"timestampFromMs":5400,"timestampToMs":18060},{"verseNumber":2,"timestampFromMs":18060,"timestampToMs":34780},{"verseNumber":3,"timestampFromMs":34780,"timestampToMs":74420},{"verseNumber":4,"timestampFromMs":74420,"timestampToMs":104620},{"verseNumber":5,"timestampFromMs":104620,"timestampToMs":135700},{"verseNumber":6,"timestampFromMs":135700,"timestampToMs":156700},{"verseNumber":7,"timestampFromMs":156700,"timestampToMs":193420},{"verseNumber":8,"timestampFromMs":193420,"timestampToMs":215380},{"verseNumber":9,"timestampFromMs":215380,"timestampToMs":233020},{"verseNumber":10,"timestampFromMs":233020,"timestampToMs":246960},{"verseNumber":11,"timestampFromMs":246960,"timestampToMs":264640},{"verseNumber":12,"timestampFromMs":264640,"timestampToMs":300960},{"verseNumber":13,"timestampFromMs":300960,"timestampToMs":329640},{"verseNumber":14,"timestampFromMs":329640,"timestampToMs":344500},{"verseNumber":15,"timestampFromMs":344500,"timestampToMs":359900},{"verseNumber":16,"timestampFromMs":359900,"timestampToMs":394100},{"verseNumber":17,"timestampFromMs":394100,"timestampToMs":419000},{"verseNumber":18,"timestampFromMs":419000,"timestampToMs":453320},{"verseNumber":19,"timestampFromMs":453320,"timestampToMs":482220},{"verseNumber":20,"timestampFromMs":482220,"timestampToMs":505300},{"verseNumber":21,"timestampFromMs":505300,"timestampToMs":521180},{"verseNumber":22,"timestampFromMs":521180,"timestampToMs":534700},{"verseNumber":23,"timestampFromMs":534700,"timestampToMs":564880},{"verseNumber":24,"timestampFromMs":564880,"timestampToMs":613800},{"verseNumber":25,"timestampFromMs":613800,"timestampToMs":639520},{"verseNumber":26,"timestampFromMs":639520,"timestampToMs":663300},{"verseNumber":27,"timestampFromMs":663300,"timestampToMs":678740},{"verseNumber":28,"timestampFromMs":678740,"timestampToMs":716180},{"verseNumber":29,"timestampFromMs":716180,"timestampToMs":748400},{"verseNumber":30,"timestampFromMs":748400,"timestampToMs":779760},{"verseNumber":31,"timestampFromMs":779760,"timestampToMs":812840},{"verseNumber":32,"timestampFromMs":812840,"timestampToMs":832400},{"verseNumber":33,"timestampFromMs":832400,"timestampToMs":846600},{"verseNumber":34,"timestampFromMs":846600,"timestampToMs":885500},{"verseNumber":35,"timestampFromMs":885500,"timestampToMs":907640},{"verseNumber":36,"timestampFromMs":907640,"timestampToMs":960660},{"verseNumber":37,"timestampFromMs":960660,"timestampToMs":1008720},{"verseNumber":38,"timestampFromMs":1008720,"timestampToMs":1038340},{"verseNumber":39,"timestampFromMs":1038340,"timestampToMs":1059760},{"verseNumber":40,"timestampFromMs":1059760,"timestampToMs":1111580},{"verseNumber":41,"timestampFromMs":1111580,"timestampToMs":1133720},{"verseNumber":42,"timestampFromMs":1133720,"timestampToMs":1164720},{"verseNumber":43,"timestampFromMs":1164720,"timestampToMs":1178700},{"verseNumber":44,"timestampFromMs":1178700,"timestampToMs":1198660},{"verseNumber":45,"timestampFromMs":1198660,"timestampToMs":1215240},{"verseNumber":46,"timestampFromMs":1215240,"timestampToMs":1232920},{"verseNumber":47,"timestampFromMs":1232920,"timestampToMs":1256140},{"verseNumber":48,"timestampFromMs":1256140,"timestampToMs":1272260},{"verseNumber":49,"timestampFromMs":1272260,"timestampToMs":1293220},{"verseNumber":50,"timestampFromMs":1293220,"timestampToMs":1314460},{"verseNumber":51,"timestampFromMs":1314460,"timestampToMs":1331140},{"verseNumber":52,"timestampFromMs":1331140,"timestampToMs":1363040},{"verseNumber":53,"timestampFromMs":1363040,"timestampToMs":1378860},{"verseNumber":54,"timestampFromMs":1378860,"timestampToMs":1411680},{"verseNumber":55,"timestampFromMs":1411680,"timestampToMs":1434760},{"verseNumber":56,"timestampFromMs":1434760,"timestampToMs":1450300},{"verseNumber":57,"timestampFromMs":1450300,"timestampToMs":1461660},{"verseNumber":58,"timestampFromMs":1461660,"timestampToMs":1477180},{"verseNumber":59,"timestampFromMs":1477180,"timestampToMs":1511400},{"verseNumber":60,"timestampFromMs":1511400,"timestampToMs":1545360},{"verseNumber":61,"timestampFromMs":1545360,"timestampToMs":1575500},{"verseNumber":62,"timestampFromMs":1575500,"timestampToMs":1591140},{"verseNumber":63,"timestampFromMs":1591140,"timestampToMs":1612880},{"verseNumber":64,"timestampFromMs":1612880,"timestampToMs":1635720},{"verseNumber":65,"timestampFromMs":1635720,"timestampToMs":1656260},{"verseNumber":66,"timestampFromMs":1656260,"timestampToMs":1681880},{"verseNumber":67,"timestampFromMs":1681880,"timestampToMs":1710920},{"verseNumber":68,"timestampFromMs":1710920,"timestampToMs":1732240},{"verseNumber":69,"timestampFromMs":1732240,"timestampToMs":1783700},{"verseNumber":70,"timestampFromMs":1783700,"timestampToMs":1819300},{"verseNumber":71,"timestampFromMs":1819300,"timestampToMs":1855020},{"verseNumber":72,"timestampFromMs":1855020,"timestampToMs":1885120},{"verseNumber":73,"timestampFromMs":1885120,"timestampToMs":1902900},{"verseNumber":74,"timestampFromMs":1902900,"timestampToMs":1954880},{"verseNumber":75,"timestampFromMs":1954880,"timestampToMs":1970780},{"verseNumber":76,"timestampFromMs":1970780,"timestampToMs":1984180},{"verseNumber":77,"timestampFromMs":1984180,"timestampToMs":2001280},{"verseNumber":78,"timestampFromMs":2001280,"timestampToMs":2015720},{"verseNumber":79,"timestampFromMs":2015720,"timestampToMs":2036440},{"verseNumber":80,"timestampFromMs":2036440,"timestampToMs":2064860},{"verseNumber":81,"timestampFromMs":2064860,"timestampToMs":2096480},{"verseNumber":82,"timestampFromMs":2096480,"timestampToMs":2109440},{"verseNumber":83,"timestampFromMs":2109440,"timestampToMs":2140660},{"verseNumber":84,"timestampFromMs":2140660,"timestampToMs":2162060},{"verseNumber":85,"timestampFromMs":2162060,"timestampToMs":2182360},{"verseNumber":86,"timestampFromMs":2182360,"timestampToMs":2201800},{"verseNumber":87,"timestampFromMs":2201800,"timestampToMs":2212800},{"verseNumber":88,"timestampFromMs":2212800,"timestampToMs":2233840},{"verseNumber":89,"timestampFromMs":2233840,"timestampToMs":2250620},{"verseNumber":90,"timestampFromMs":2250620,"timestampToMs":2270740},{"verseNumber":91,"timestampFromMs":2270740,"timestampToMs":2298120},{"verseNumber":92,"timestampFromMs":2298120,"timestampToMs":2321200},{"verseNumber":93,"timestampFromMs":2321200,"timestampToMs":2343160},{"verseNumber":94,"timestampFromMs":2343160,"timestampToMs":2385120},{"verseNumber":95,"timestampFromMs":2385120,"timestampToMs":2411740},{"verseNumber":96,"timestampFromMs":2411740,"timestampToMs":2427800},{"verseNumber":97,"timestampFromMs":2427800,"timestampToMs":2447520},{"verseNumber":98,"timestampFromMs":2447520,"timestampToMs":2470200},{"verseNumber":99,"timestampFromMs":2470200,"timestampToMs":2503600},{"verseNumber":100,"timestampFromMs":2503600,"timestampToMs":2541480},{"verseNumber":101,"timestampFromMs":2541480,"timestampToMs":2569020},{"verseNumber":102,"timestampFromMs":2569020,"timestampToMs":2589780},{"verseNumber":103,"timestampFromMs":2589780,"timestampToMs":2609120},{"verseNumber":104,"timestampFromMs":2609120,"timestampToMs":2626760},{"verseNumber":105,"timestampFromMs":2626760,"timestampToMs":2653680},{"verseNumber":106,"timestampFromMs":2653680,"timestampToMs":2669360},{"verseNumber":107,"timestampFromMs":2669360,"timestampToMs":2701180},{"verseNumber":108,"timestampFromMs":2701180,"timestampToMs":2728040},{"verseNumber":109,"timestampFromMs":2728040,"timestampToMs":2754820},{"verseNumber":110,"timestampFromMs":2754820,"timestampToMs":2773080},{"verseNumber":111,"timestampFromMs":2773080,"timestampToMs":2822240},{"verseNumber":112,"timestampFromMs":2822240,"timestampToMs":2850940},{"verseNumber":113,"timestampFromMs":2850940,"timestampToMs":2874820},{"verseNumber":114,"timestampFromMs":2874820,"timestampToMs":2904740},{"verseNumber":115,"timestampFromMs":2904740,"timestampToMs":2924620},{"verseNumber":116,"timestampFromMs":2924620,"timestampToMs":2943820},{"verseNumber":117,"timestampFromMs":2943820,"timestampToMs":2973720},{"verseNumber":118,"timestampFromMs":2973720,"timestampToMs":3008260},{"verseNumber":119,"timestampFromMs":3008260,"timestampToMs":3018660},{"verseNumber":120,"timestampFromMs":3018660,"timestampToMs":3080060},{"verseNumber":121,"timestampFromMs":3080060,"timestampToMs":3100940},{"verseNumber":122,"timestampFromMs":3100940,"timestampToMs":3133380},{"verseNumber":123,"timestampFromMs":3133380,"timestampToMs":3155580},{"verseNumber":124,"timestampFromMs":3155580,"timestampToMs":3183260},{"verseNumber":125,"timestampFromMs":3183260,"timestampToMs":3198100},{"verseNumber":126,"timestampFromMs":3198100,"timestampToMs":3215280},{"verseNumber":127,"timestampFromMs":3215280,"timestampToMs":3242580},{"verseNumber":128,"timestampFromMs":3242580,"timestampToMs":3261220},{"verseNumber":129,"timestampFromMs":3261220,"timestampToMs":3276020}],"alignment":{"source":"ctc-forced-aligner:jonatasgrosman/wav2vec2-large-xlsr-53-arabic","wordMatchRatio":1.0,"alignedAt":"2026-04-21T16:36:49+00:00"}}