{"audioUrl":"https://pub-ec086546d4bd484d9518e7dad253ff6e.r2.dev/37-abdulbaset-murattal-ar/097.mp3","totalDurationMs":40568,"timings":[{"verseNumber":1,"timestampFromMs":4840,"timestampToMs":12620},{"verseNumber":2,"timestampFromMs":12620,"timestampToMs":18440},{"verseNumber":3,"timestampFromMs":18440,"timestampToMs":24180},{"verseNumber":4,"timestampFromMs":24180,"timestampToMs":35500},{"verseNumber":5,"timestampFromMs":35500,"timestampToMs":39740}],"alignment":{"source":"ctc-forced-aligner:jonatasgrosman/wav2vec2-large-xlsr-53-arabic","wordMatchRatio":1.0,"alignedAt":"2026-04-21T17:55:02+00:00"}}