{"audioUrl":"https://pub-ec086546d4bd484d9518e7dad253ff6e.r2.dev/06-minshawi-murattal-ar/005.mp3","totalDurationMs":4035553,"timings":[{"verseNumber":1,"timestampFromMs":10040,"timestampToMs":39280},{"verseNumber":2,"timestampFromMs":39280,"timestampToMs":121120},{"verseNumber":3,"timestampFromMs":121120,"timestampToMs":220520},{"verseNumber":4,"timestampFromMs":220520,"timestampToMs":277600},{"verseNumber":5,"timestampFromMs":277600,"timestampToMs":362180},{"verseNumber":6,"timestampFromMs":362180,"timestampToMs":487000},{"verseNumber":7,"timestampFromMs":487000,"timestampToMs":517560},{"verseNumber":8,"timestampFromMs":517560,"timestampToMs":561560},{"verseNumber":9,"timestampFromMs":561560,"timestampToMs":577240},{"verseNumber":10,"timestampFromMs":577240,"timestampToMs":591820},{"verseNumber":11,"timestampFromMs":591820,"timestampToMs":641460},{"verseNumber":12,"timestampFromMs":641460,"timestampToMs":732720},{"verseNumber":13,"timestampFromMs":732720,"timestampToMs":793500},{"verseNumber":14,"timestampFromMs":793500,"timestampToMs":845440},{"verseNumber":15,"timestampFromMs":845440,"timestampToMs":898980},{"verseNumber":16,"timestampFromMs":898980,"timestampToMs":939180},{"verseNumber":17,"timestampFromMs":939180,"timestampToMs":993840},{"verseNumber":18,"timestampFromMs":993840,"timestampToMs":1048520},{"verseNumber":19,"timestampFromMs":1048520,"timestampToMs":1091620},{"verseNumber":20,"timestampFromMs":1091620,"timestampToMs":1120060},{"verseNumber":21,"timestampFromMs":1120060,"timestampToMs":1136940},{"verseNumber":22,"timestampFromMs":1136940,"timestampToMs":1167160},{"verseNumber":23,"timestampFromMs":1167160,"timestampToMs":1194680},{"verseNumber":24,"timestampFromMs":1194680,"timestampToMs":1218420},{"verseNumber":25,"timestampFromMs":1218420,"timestampToMs":1233440},{"verseNumber":26,"timestampFromMs":1233440,"timestampToMs":1250700},{"verseNumber":27,"timestampFromMs":1250700,"timestampToMs":1281080},{"verseNumber":28,"timestampFromMs":1281080,"timestampToMs":1302420},{"verseNumber":29,"timestampFromMs":1302420,"timestampToMs":1322160},{"verseNumber":30,"timestampFromMs":1322160,"timestampToMs":1332420},{"verseNumber":31,"timestampFromMs":1332420,"timestampToMs":1360760},{"verseNumber":32,"timestampFromMs":1360760,"timestampToMs":1428720},{"verseNumber":33,"timestampFromMs":1428720,"timestampToMs":1471500},{"verseNumber":34,"timestampFromMs":1471500,"timestampToMs":1487520},{"verseNumber":35,"timestampFromMs":1487520,"timestampToMs":1505580},{"verseNumber":36,"timestampFromMs":1505580,"timestampToMs":1529020},{"verseNumber":37,"timestampFromMs":1529020,"timestampToMs":1544260},{"verseNumber":38,"timestampFromMs":1544260,"timestampToMs":1562900},{"verseNumber":39,"timestampFromMs":1562900,"timestampToMs":1579320},{"verseNumber":40,"timestampFromMs":1579320,"timestampToMs":1604220},{"verseNumber":41,"timestampFromMs":1604220,"timestampToMs":1682600},{"verseNumber":42,"timestampFromMs":1682600,"timestampToMs":1718180},{"verseNumber":43,"timestampFromMs":1718180,"timestampToMs":1739120},{"verseNumber":44,"timestampFromMs":1739120,"timestampToMs":1802840},{"verseNumber":45,"timestampFromMs":1802840,"timestampToMs":1846940},{"verseNumber":46,"timestampFromMs":1846940,"timestampToMs":1879000},{"verseNumber":47,"timestampFromMs":1879000,"timestampToMs":1901940},{"verseNumber":48,"timestampFromMs":1901940,"timestampToMs":1974360},{"verseNumber":49,"timestampFromMs":1974360,"timestampToMs":2019280},{"verseNumber":50,"timestampFromMs":2019280,"timestampToMs":2032880},{"verseNumber":51,"timestampFromMs":2032880,"timestampToMs":2067680},{"verseNumber":52,"timestampFromMs":2067680,"timestampToMs":2102320},{"verseNumber":53,"timestampFromMs":2102320,"timestampToMs":2125320},{"verseNumber":54,"timestampFromMs":2125320,"timestampToMs":2184020},{"verseNumber":55,"timestampFromMs":2184020,"timestampToMs":2199940},{"verseNumber":56,"timestampFromMs":2199940,"timestampToMs":2213000},{"verseNumber":57,"timestampFromMs":2213000,"timestampToMs":2251700},{"verseNumber":58,"timestampFromMs":2251700,"timestampToMs":2266600},{"verseNumber":59,"timestampFromMs":2266600,"timestampToMs":2299300},{"verseNumber":60,"timestampFromMs":2299300,"timestampToMs":2333880},{"verseNumber":61,"timestampFromMs":2333880,"timestampToMs":2353080},{"verseNumber":62,"timestampFromMs":2353080,"timestampToMs":2368960},{"verseNumber":63,"timestampFromMs":2368960,"timestampToMs":2385840},{"verseNumber":64,"timestampFromMs":2385840,"timestampToMs":2450540},{"verseNumber":65,"timestampFromMs":2450540,"timestampToMs":2467980},{"verseNumber":66,"timestampFromMs":2467980,"timestampToMs":2502300},{"verseNumber":67,"timestampFromMs":2502300,"timestampToMs":2531900},{"verseNumber":68,"timestampFromMs":2531900,"timestampToMs":2571160},{"verseNumber":69,"timestampFromMs":2571160,"timestampToMs":2600160},{"verseNumber":70,"timestampFromMs":2600160,"timestampToMs":2630680},{"verseNumber":71,"timestampFromMs":2630680,"timestampToMs":2656100},{"verseNumber":72,"timestampFromMs":2656100,"timestampToMs":2697220},{"verseNumber":73,"timestampFromMs":2697220,"timestampToMs":2727200},{"verseNumber":74,"timestampFromMs":2727200,"timestampToMs":2738320},{"verseNumber":75,"timestampFromMs":2738320,"timestampToMs":2768040},{"verseNumber":76,"timestampFromMs":2768040,"timestampToMs":2784620},{"verseNumber":77,"timestampFromMs":2784620,"timestampToMs":2823540},{"verseNumber":78,"timestampFromMs":2823540,"timestampToMs":2843840},{"verseNumber":79,"timestampFromMs":2843840,"timestampToMs":2857220},{"verseNumber":80,"timestampFromMs":2857220,"timestampToMs":2878720},{"verseNumber":81,"timestampFromMs":2878720,"timestampToMs":2900300},{"verseNumber":82,"timestampFromMs":2900300,"timestampToMs":2939720},{"verseNumber":83,"timestampFromMs":2939720,"timestampToMs":2966700},{"verseNumber":84,"timestampFromMs":2966700,"timestampToMs":2983580},{"verseNumber":85,"timestampFromMs":2983580,"timestampToMs":3004000},{"verseNumber":86,"timestampFromMs":3004000,"timestampToMs":3016160},{"verseNumber":87,"timestampFromMs":3016160,"timestampToMs":3036780},{"verseNumber":88,"timestampFromMs":3036780,"timestampToMs":3053240},{"verseNumber":89,"timestampFromMs":3053240,"timestampToMs":3112060},{"verseNumber":90,"timestampFromMs":3112060,"timestampToMs":3135180},{"verseNumber":91,"timestampFromMs":3135180,"timestampToMs":3162440},{"verseNumber":92,"timestampFromMs":3162440,"timestampToMs":3181800},{"verseNumber":93,"timestampFromMs":3181800,"timestampToMs":3217340},{"verseNumber":94,"timestampFromMs":3217340,"timestampToMs":3248980},{"verseNumber":95,"timestampFromMs":3248980,"timestampToMs":3317800},{"verseNumber":96,"timestampFromMs":3317800,"timestampToMs":3343300},{"verseNumber":97,"timestampFromMs":3343300,"timestampToMs":3377460},{"verseNumber":98,"timestampFromMs":3377460,"timestampToMs":3390120},{"verseNumber":99,"timestampFromMs":3390120,"timestampToMs":3402160},{"verseNumber":100,"timestampFromMs":3402160,"timestampToMs":3421400},{"verseNumber":101,"timestampFromMs":3421400,"timestampToMs":3450780},{"verseNumber":102,"timestampFromMs":3450780,"timestampToMs":3461740},{"verseNumber":103,"timestampFromMs":3461740,"timestampToMs":3496180},{"verseNumber":104,"timestampFromMs":3496180,"timestampToMs":3525540},{"verseNumber":105,"timestampFromMs":3525540,"timestampToMs":3550800},{"verseNumber":106,"timestampFromMs":3550800,"timestampToMs":3619900},{"verseNumber":107,"timestampFromMs":3619900,"timestampToMs":3658520},{"verseNumber":108,"timestampFromMs":3658520,"timestampToMs":3689480},{"verseNumber":109,"timestampFromMs":3689480,"timestampToMs":3707600},{"verseNumber":110,"timestampFromMs":3707600,"timestampToMs":3782580},{"verseNumber":111,"timestampFromMs":3782580,"timestampToMs":3798340},{"verseNumber":112,"timestampFromMs":3798340,"timestampToMs":3824320},{"verseNumber":113,"timestampFromMs":3824320,"timestampToMs":3840820},{"verseNumber":114,"timestampFromMs":3840820,"timestampToMs":3873520},{"verseNumber":115,"timestampFromMs":3873520,"timestampToMs":3897200},{"verseNumber":116,"timestampFromMs":3897200,"timestampToMs":3942840},{"verseNumber":117,"timestampFromMs":3942840,"timestampToMs":3975780},{"verseNumber":118,"timestampFromMs":3975780,"timestampToMs":3990260},{"verseNumber":119,"timestampFromMs":3990260,"timestampToMs":4018500},{"verseNumber":120,"timestampFromMs":4018500,"timestampToMs":4030400}],"alignment":{"source":"ctc-forced-aligner:jonatasgrosman/wav2vec2-large-xlsr-53-arabic","wordMatchRatio":1.0,"alignedAt":"2026-04-21T06:57:33+00:00"}}