{"audioUrl":"https://pub-ec086546d4bd484d9518e7dad253ff6e.r2.dev/06-minshawi-murattal-ar/065.mp3","totalDurationMs":374779,"timings":[{"verseNumber":1,"timestampFromMs":6640,"timestampToMs":53040},{"verseNumber":2,"timestampFromMs":53040,"timestampToMs":86780},{"verseNumber":3,"timestampFromMs":86780,"timestampToMs":106920},{"verseNumber":4,"timestampFromMs":106920,"timestampToMs":144260},{"verseNumber":5,"timestampFromMs":144260,"timestampToMs":162560},{"verseNumber":6,"timestampFromMs":162560,"timestampToMs":214680},{"verseNumber":7,"timestampFromMs":214680,"timestampToMs":247040},{"verseNumber":8,"timestampFromMs":247040,"timestampToMs":272800},{"verseNumber":9,"timestampFromMs":272800,"timestampToMs":281060},{"verseNumber":10,"timestampFromMs":281060,"timestampToMs":301020},{"verseNumber":11,"timestampFromMs":301020,"timestampToMs":328440},{"verseNumber":12,"timestampFromMs":328440,"timestampToMs":335720}],"alignment":{"source":"ctc-forced-aligner:jonatasgrosman/wav2vec2-large-xlsr-53-arabic","wordMatchRatio":1.0,"alignedAt":"2026-04-21T08:16:50+00:00"}}