{"audioUrl":"https://pub-ec086546d4bd484d9518e7dad253ff6e.r2.dev/06-minshawi-murattal-ar/086.mp3","totalDurationMs":105038,"timings":[{"verseNumber":1,"timestampFromMs":5680,"timestampToMs":10800},{"verseNumber":2,"timestampFromMs":10800,"timestampToMs":16880},{"verseNumber":3,"timestampFromMs":16880,"timestampToMs":21040},{"verseNumber":4,"timestampFromMs":21040,"timestampToMs":29040},{"verseNumber":5,"timestampFromMs":29040,"timestampToMs":36380},{"verseNumber":6,"timestampFromMs":36380,"timestampToMs":42680},{"verseNumber":7,"timestampFromMs":42680,"timestampToMs":50960},{"verseNumber":8,"timestampFromMs":50960,"timestampToMs":57340},{"verseNumber":9,"timestampFromMs":57340,"timestampToMs":62420},{"verseNumber":10,"timestampFromMs":62420,"timestampToMs":69760},{"verseNumber":11,"timestampFromMs":69760,"timestampToMs":75120},{"verseNumber":12,"timestampFromMs":75120,"timestampToMs":79040},{"verseNumber":13,"timestampFromMs":79040,"timestampToMs":84380},{"verseNumber":14,"timestampFromMs":84380,"timestampToMs":87680},{"verseNumber":15,"timestampFromMs":87680,"timestampToMs":93260},{"verseNumber":16,"timestampFromMs":93260,"timestampToMs":96680},{"verseNumber":17,"timestampFromMs":96680,"timestampToMs":103760}],"alignment":{"source":"ctc-forced-aligner:jonatasgrosman/wav2vec2-large-xlsr-53-arabic","wordMatchRatio":1.0,"alignedAt":"2026-04-21T08:23:43+00:00"}}