{"audioUrl":"https://pub-ec086546d4bd484d9518e7dad253ff6e.r2.dev/27-rifai-murattal-ar/067.mp3","totalDurationMs":363964,"timings":[{"verseNumber":1,"timestampFromMs":5140,"timestampToMs":13620},{"verseNumber":2,"timestampFromMs":13620,"timestampToMs":25000},{"verseNumber":3,"timestampFromMs":25000,"timestampToMs":41040},{"verseNumber":4,"timestampFromMs":41040,"timestampToMs":51380},{"verseNumber":5,"timestampFromMs":51380,"timestampToMs":67200},{"verseNumber":6,"timestampFromMs":67200,"timestampToMs":75560},{"verseNumber":7,"timestampFromMs":75560,"timestampToMs":83640},{"verseNumber":8,"timestampFromMs":83640,"timestampToMs":100140},{"verseNumber":9,"timestampFromMs":100140,"timestampToMs":118580},{"verseNumber":10,"timestampFromMs":118580,"timestampToMs":128860},{"verseNumber":11,"timestampFromMs":128860,"timestampToMs":137280},{"verseNumber":12,"timestampFromMs":137280,"timestampToMs":148640},{"verseNumber":13,"timestampFromMs":148640,"timestampToMs":157740},{"verseNumber":14,"timestampFromMs":157740,"timestampToMs":163560},{"verseNumber":15,"timestampFromMs":163560,"timestampToMs":176180},{"verseNumber":16,"timestampFromMs":176180,"timestampToMs":187360},{"verseNumber":17,"timestampFromMs":187360,"timestampToMs":200220},{"verseNumber":18,"timestampFromMs":200220,"timestampToMs":207920},{"verseNumber":19,"timestampFromMs":207920,"timestampToMs":226680},{"verseNumber":20,"timestampFromMs":226680,"timestampToMs":241180},{"verseNumber":21,"timestampFromMs":241180,"timestampToMs":252320},{"verseNumber":22,"timestampFromMs":252320,"timestampToMs":265960},{"verseNumber":23,"timestampFromMs":265960,"timestampToMs":278760},{"verseNumber":24,"timestampFromMs":278760,"timestampToMs":285700},{"verseNumber":25,"timestampFromMs":285700,"timestampToMs":293540},{"verseNumber":26,"timestampFromMs":293540,"timestampToMs":302840},{"verseNumber":27,"timestampFromMs":302840,"timestampToMs":317580},{"verseNumber":28,"timestampFromMs":317580,"timestampToMs":330500},{"verseNumber":29,"timestampFromMs":330500,"timestampToMs":343460},{"verseNumber":30,"timestampFromMs":343460,"timestampToMs":354900}],"alignment":{"source":"ctc-forced-aligner:jonatasgrosman/wav2vec2-large-xlsr-53-arabic","wordMatchRatio":1.0,"alignedAt":"2026-04-21T15:44:59+00:00"}}