{"audioUrl":"https://pub-ec086546d4bd484d9518e7dad253ff6e.r2.dev/16-husary-murattal-ar/023.mp3","totalDurationMs":2128457,"timings":[{"verseNumber":1,"timestampFromMs":9360,"timestampToMs":16440},{"verseNumber":2,"timestampFromMs":16440,"timestampToMs":25480},{"verseNumber":3,"timestampFromMs":25480,"timestampToMs":34720},{"verseNumber":4,"timestampFromMs":34720,"timestampToMs":45040},{"verseNumber":5,"timestampFromMs":45040,"timestampToMs":55740},{"verseNumber":6,"timestampFromMs":55740,"timestampToMs":77120},{"verseNumber":7,"timestampFromMs":77120,"timestampToMs":93800},{"verseNumber":8,"timestampFromMs":93800,"timestampToMs":106680},{"verseNumber":9,"timestampFromMs":106680,"timestampToMs":118620},{"verseNumber":10,"timestampFromMs":118620,"timestampToMs":130080},{"verseNumber":11,"timestampFromMs":130080,"timestampToMs":146240},{"verseNumber":12,"timestampFromMs":146240,"timestampToMs":160540},{"verseNumber":13,"timestampFromMs":160540,"timestampToMs":174720},{"verseNumber":14,"timestampFromMs":174720,"timestampToMs":221540},{"verseNumber":15,"timestampFromMs":221540,"timestampToMs":233720},{"verseNumber":16,"timestampFromMs":233720,"timestampToMs":245760},{"verseNumber":17,"timestampFromMs":245760,"timestampToMs":265700},{"verseNumber":18,"timestampFromMs":265700,"timestampToMs":295100},{"verseNumber":19,"timestampFromMs":295100,"timestampToMs":324040},{"verseNumber":20,"timestampFromMs":324040,"timestampToMs":346660},{"verseNumber":21,"timestampFromMs":346660,"timestampToMs":382280},{"verseNumber":22,"timestampFromMs":382280,"timestampToMs":393320},{"verseNumber":23,"timestampFromMs":393320,"timestampToMs":421680},{"verseNumber":24,"timestampFromMs":421680,"timestampToMs":486400},{"verseNumber":25,"timestampFromMs":486400,"timestampToMs":505600},{"verseNumber":26,"timestampFromMs":505600,"timestampToMs":517000},{"verseNumber":27,"timestampFromMs":517000,"timestampToMs":582500},{"verseNumber":28,"timestampFromMs":582500,"timestampToMs":607180},{"verseNumber":29,"timestampFromMs":607180,"timestampToMs":626840},{"verseNumber":30,"timestampFromMs":626840,"timestampToMs":645380},{"verseNumber":31,"timestampFromMs":645380,"timestampToMs":661280},{"verseNumber":32,"timestampFromMs":661280,"timestampToMs":686440},{"verseNumber":33,"timestampFromMs":686440,"timestampToMs":737320},{"verseNumber":34,"timestampFromMs":737320,"timestampToMs":752720},{"verseNumber":35,"timestampFromMs":752720,"timestampToMs":774140},{"verseNumber":36,"timestampFromMs":774140,"timestampToMs":783660},{"verseNumber":37,"timestampFromMs":783660,"timestampToMs":800800},{"verseNumber":38,"timestampFromMs":800800,"timestampToMs":818560},{"verseNumber":39,"timestampFromMs":818560,"timestampToMs":828500},{"verseNumber":40,"timestampFromMs":828500,"timestampToMs":842680},{"verseNumber":41,"timestampFromMs":842680,"timestampToMs":866860},{"verseNumber":42,"timestampFromMs":866860,"timestampToMs":880940},{"verseNumber":43,"timestampFromMs":880940,"timestampToMs":894720},{"verseNumber":44,"timestampFromMs":894720,"timestampToMs":937700},{"verseNumber":45,"timestampFromMs":937700,"timestampToMs":949120},{"verseNumber":46,"timestampFromMs":949120,"timestampToMs":959060},{"verseNumber":47,"timestampFromMs":959060,"timestampToMs":970860},{"verseNumber":48,"timestampFromMs":970860,"timestampToMs":978000},{"verseNumber":49,"timestampFromMs":978000,"timestampToMs":987360},{"verseNumber":50,"timestampFromMs":987360,"timestampToMs":1008980},{"verseNumber":51,"timestampFromMs":1008980,"timestampToMs":1027800},{"verseNumber":52,"timestampFromMs":1027800,"timestampToMs":1044640},{"verseNumber":53,"timestampFromMs":1044640,"timestampToMs":1061660},{"verseNumber":54,"timestampFromMs":1061660,"timestampToMs":1069760},{"verseNumber":55,"timestampFromMs":1069760,"timestampToMs":1082240},{"verseNumber":56,"timestampFromMs":1082240,"timestampToMs":1094240},{"verseNumber":57,"timestampFromMs":1094240,"timestampToMs":1105800},{"verseNumber":58,"timestampFromMs":1105800,"timestampToMs":1115080},{"verseNumber":59,"timestampFromMs":1115080,"timestampToMs":1123580},{"verseNumber":60,"timestampFromMs":1123580,"timestampToMs":1142240},{"verseNumber":61,"timestampFromMs":1142240,"timestampToMs":1156320},{"verseNumber":62,"timestampFromMs":1156320,"timestampToMs":1174400},{"verseNumber":63,"timestampFromMs":1174400,"timestampToMs":1192860},{"verseNumber":64,"timestampFromMs":1192860,"timestampToMs":1208780},{"verseNumber":65,"timestampFromMs":1208780,"timestampToMs":1221220},{"verseNumber":66,"timestampFromMs":1221220,"timestampToMs":1237800},{"verseNumber":67,"timestampFromMs":1237800,"timestampToMs":1247040},{"verseNumber":68,"timestampFromMs":1247040,"timestampToMs":1264180},{"verseNumber":69,"timestampFromMs":1264180,"timestampToMs":1275040},{"verseNumber":70,"timestampFromMs":1275040,"timestampToMs":1296400},{"verseNumber":71,"timestampFromMs":1296400,"timestampToMs":1328200},{"verseNumber":72,"timestampFromMs":1328200,"timestampToMs":1344560},{"verseNumber":73,"timestampFromMs":1344560,"timestampToMs":1355420},{"verseNumber":74,"timestampFromMs":1355420,"timestampToMs":1368820},{"verseNumber":75,"timestampFromMs":1368820,"timestampToMs":1386740},{"verseNumber":76,"timestampFromMs":1386740,"timestampToMs":1402760},{"verseNumber":77,"timestampFromMs":1402760,"timestampToMs":1423180},{"verseNumber":78,"timestampFromMs":1423180,"timestampToMs":1443060},{"verseNumber":79,"timestampFromMs":1443060,"timestampToMs":1454340},{"verseNumber":80,"timestampFromMs":1454340,"timestampToMs":1476400},{"verseNumber":81,"timestampFromMs":1476400,"timestampToMs":1487860},{"verseNumber":82,"timestampFromMs":1487860,"timestampToMs":1505460},{"verseNumber":83,"timestampFromMs":1505460,"timestampToMs":1529620},{"verseNumber":84,"timestampFromMs":1529620,"timestampToMs":1544860},{"verseNumber":85,"timestampFromMs":1544860,"timestampToMs":1557920},{"verseNumber":86,"timestampFromMs":1557920,"timestampToMs":1570700},{"verseNumber":87,"timestampFromMs":1570700,"timestampToMs":1583480},{"verseNumber":88,"timestampFromMs":1583480,"timestampToMs":1604740},{"verseNumber":89,"timestampFromMs":1604740,"timestampToMs":1618180},{"verseNumber":90,"timestampFromMs":1618180,"timestampToMs":1632400},{"verseNumber":91,"timestampFromMs":1632400,"timestampToMs":1668560},{"verseNumber":92,"timestampFromMs":1668560,"timestampToMs":1681560},{"verseNumber":93,"timestampFromMs":1681560,"timestampToMs":1693020},{"verseNumber":94,"timestampFromMs":1693020,"timestampToMs":1703440},{"verseNumber":95,"timestampFromMs":1703440,"timestampToMs":1717120},{"verseNumber":96,"timestampFromMs":1717120,"timestampToMs":1733320},{"verseNumber":97,"timestampFromMs":1733320,"timestampToMs":1744460},{"verseNumber":98,"timestampFromMs":1744460,"timestampToMs":1753520},{"verseNumber":99,"timestampFromMs":1753520,"timestampToMs":1768580},{"verseNumber":100,"timestampFromMs":1768580,"timestampToMs":1805560},{"verseNumber":101,"timestampFromMs":1805560,"timestampToMs":1824360},{"verseNumber":102,"timestampFromMs":1824360,"timestampToMs":1837320},{"verseNumber":103,"timestampFromMs":1837320,"timestampToMs":1859900},{"verseNumber":104,"timestampFromMs":1859900,"timestampToMs":1872420},{"verseNumber":105,"timestampFromMs":1872420,"timestampToMs":1887940},{"verseNumber":106,"timestampFromMs":1887940,"timestampToMs":1907000},{"verseNumber":107,"timestampFromMs":1907000,"timestampToMs":1922380},{"verseNumber":108,"timestampFromMs":1922380,"timestampToMs":1932680},{"verseNumber":109,"timestampFromMs":1932680,"timestampToMs":1960640},{"verseNumber":110,"timestampFromMs":1960640,"timestampToMs":1983460},{"verseNumber":111,"timestampFromMs":1983460,"timestampToMs":2002340},{"verseNumber":112,"timestampFromMs":2002340,"timestampToMs":2012300},{"verseNumber":113,"timestampFromMs":2012300,"timestampToMs":2028820},{"verseNumber":114,"timestampFromMs":2028820,"timestampToMs":2045620},{"verseNumber":115,"timestampFromMs":2045620,"timestampToMs":2063100},{"verseNumber":116,"timestampFromMs":2063100,"timestampToMs":2084040},{"verseNumber":117,"timestampFromMs":2084040,"timestampToMs":2113480},{"verseNumber":118,"timestampFromMs":2113480,"timestampToMs":2124700}],"alignment":{"source":"ctc-forced-aligner:jonatasgrosman/wav2vec2-large-xlsr-53-arabic","wordMatchRatio":1.0,"alignedAt":"2026-04-21T11:26:26+00:00"}}